<?xml version="1.0" encoding="utf-8" ?><dwsync><file name="index.html" server="ftp.arthurmcneil.com//public_html/" local="3297813240" remote="1973247548337464056" /><file name="mw_box_bl.png" server="ftp.arthurmcneil.com//public_html/" local="3297813240" remote="1973554964916642552" /><file name="mw_box_br.png" server="ftp.arthurmcneil.com//public_html/" local="3297813240" remote="1973565135399199480" /><file name="mw_box_tl.png" server="ftp.arthurmcneil.com//public_html/" local="3297813240" remote="1973659916737487608" /><file name="mw_box_tr.png" server="ftp.arthurmcneil.com//public_html/" local="3297813240" remote="1973665637633925880" /><file name="mw_footer_b.png" server="ftp.arthurmcneil.com//public_html/" local="3297813240" remote="1973671358530364152" /><file name="mw_footer_b_l.png" server="ftp.arthurmcneil.com//public_html/" local="3297813240" remote="1973677079426802424" /><file name="mw_footer_b_r.png" server="ftp.arthurmcneil.com//public_html/" local="3297813240" remote="1973687249909359352" /><file name="mw_header_t.png" server="ftp.arthurmcneil.com//public_html/" local="3297813240" remote="1973692335150637816" /><file name="mw_header_t_l.png" server="ftp.arthurmcneil.com//public_html/" local="3297813240" remote="1973691699495478008" /><file name="mw_header_t_r.png" server="ftp.arthurmcneil.com//public_html/" local="3297813240" remote="1973765813451137784" /><file name="mw_menu_active_bg.png" server="ftp.arthurmcneil.com//public_html/" local="3297813240" remote="1973770898692416248" /><file name="mw_shadow_l.png" server="ftp.arthurmcneil.com//public_html/" local="3297813240" remote="1973775983933694712" /><file name="mw_shadow_r.png" server="ftp.arthurmcneil.com//public_html/" local="3297813240" remote="1973775348278534904" /></dwsync>